dochap_tool
