Metadata-Version: 1.0
Name: dochap-tool
Version: 1.2.0
Summary: Tool for handling genetic transcripts
Home-page: https://github.com/nitzanel/dochap_tool
Author: Nitzan Elbaz
Author-email: elbazni@post.bgu.ac.il
License: UNKNOWN
Platform: UNKNOWN
